xaal/__init__.py
xaal/lib/__init__.py
xaal/lib/__main__.py
xaal/lib/aioengine.py
xaal/lib/aiohelpers.py
xaal/lib/aionetwork.py
xaal/lib/bindings.py
xaal/lib/cbor.py
xaal/lib/config.py
xaal/lib/core.py
xaal/lib/devices.py
xaal/lib/engine.py
xaal/lib/exceptions.py
xaal/lib/helpers.py
xaal/lib/messages.py
xaal/lib/network.py
xaal/lib/test.py
xaal/lib/tools.py
xaal_lib-0.7.14.dist-info/METADATA
xaal_lib-0.7.14.dist-info/WHEEL
xaal_lib-0.7.14.dist-info/top_level.txt
xaal_lib-0.7.14.dist-info/RECORD
