Metadata-Version: 2.4
Name: xaal.lib
Version: 0.7.14
Summary: Official Python stack for xAAL protocol
Author-email: Jerome Kerdreux <Jerome.Kerdreux@imt-atlantique.fr>
License-Expression: GPL-3.0-or-later
Project-URL: Homepage, https://gitlab.imt-atlantique.fr/xaal/code/python/-/blob/main/packages.rst
Project-URL: Documentation, https://gitlab.imt-atlantique.fr/xaal/code/python/-/blob/main/libs/lib/README.rst
Project-URL: Source, https://gitlab.imt-atlantique.fr/xaal/code/python/-/tree/main/libs/lib
Keywords: xaal,home-automation
Classifier: Programming Language :: Python
Classifier: Topic :: Software Development :: Libraries :: Python Modules
Classifier: Topic :: Home Automation
Requires-Dist: cbor2==5.4.2
Requires-Dist: pysodium
Requires-Dist: configobj
Requires-Dist: coloredlogs
Requires-Dist: decorator
Requires-Dist: tabulate
Requires-Dist: aioconsole
